{"text": "北大应参加国际学术论坛的讨论，成为推动世界学术前进的力量。", "entity_list": []}
{"text": "在中华文化复兴的过程中，北大应能做出重大的贡献。", "entity_list": [{"type": "ns", "argument": ""}, {"type": "ns", "argument": ""}, {"type": "ns", "argument": "在中华"}, {"type": "ns", "argument": "中"}, {"type": "ns", "argument": "中华"}, {"type": "ns", "argument": "中华文"}, {"type": "ns", "argument": "中华文化"}, {"type": "ns", "argument": "中华文化复"}, {"type": "ns", "argument": "华"}, {"type": "ns", "argument": "华文"}]}
{"text": "经过一百多年的刻苦奋斗，中国文化必将赶上西方文化前进的步伐，再次走向世界文化的前列。", "entity_list": [{"type": "ns", "argument": "中"}, {"type": "ns", "argument": "中国"}, {"type": "ns", "argument": "国"}]}
{"text": "中华文化在十五世纪以前本居于世界的前列，十六世纪以后，中国落后了。", "entity_list": [{"type": "ns", "argument": ""}, {"type": "ns", "argument": ""}, {"type": "ns", "argument": ""}, {"type": "ns", "argument": "中"}, {"type": "ns", "argument": "中华"}, {"type": "ns", "argument": "中华文"}, {"type": "ns", "argument": "中华文化"}, {"type": "ns", "argument": "中华文化在"}, {"type": "ns", "argument": "中华文化在十"}, {"type": "ns", "argument": "中华文化在十五"}, {"type": "ns", "argument": "中华文化在十五世纪"}, {"type": "ns", "argument": "中华文化在十五世纪以"}, {"type": "ns", "argument": "中华文化在十五世纪以前本"}, {"type": "ns", "argument": "中华文化在十五世纪以前本居"}, {"type": "ns", "argument": "中华文化在十五世纪以前本居于"}, {"type": "ns", "argument": "中华文化在十五世纪以前本居于世"}, {"type": "ns", "argument": "中华文化在十五世纪以前本居于世界"}, {"type": "ns", "argument": "中华文化在十五世纪以前本居于世界的前列，十六世纪"}, {"type": "ns", "argument": "中华文化在十五世纪以前本居于世界的前列，十六世纪以"}, {"type": "ns", "argument": "中华文化在十五世纪以前本居于世界的前列，十六世纪以后"}, {"type": "ns", "argument": "中华文化在十五世纪以前本居于世界的前列，十六世纪以后，中"}, {"type": "ns", "argument": "中华文化在十五世纪以前本居于世界的前列，十六世纪以后，中国"}, {"type": "ns", "argument": "中华文化在十五世纪以前本居于世界的前列，十六世纪以后，中国落"}, {"type": "ns", "argument": "中华文化在十五世纪以前本居于世界的前列，十六世纪以后，中国落后"}, {"type": "ns", "argument": "中华文化在十五世纪以前本居于世界的前列，十六世纪以后，中国落后了"}, {"type": "ns", "argument": "中华文化在十五世纪以前本居于世界的前列，十六世纪以后，中国落后了。"}, {"type": "ns", "argument": "华"}, {"type": "ns", "argument": "华文"}, {"type": "ns", "argument": "华文化在十五世纪以前本居于世界的前列，十六世纪以后，中国"}, {"type": "ns", "argument": "华文化在十五世纪以前本居于世界的前列，十六世纪以后，中国落"}, {"type": "ns", "argument": "华文化在十五世纪以前本居于世界的前列，十六世纪以后，中国落后"}, {"type": "ns", "argument": "中"}, {"type": "ns", "argument": "中国"}, {"type": "ns", "argument": "中国落"}, {"type": "ns", "argument": "中国落后"}, {"type": "ns", "argument": "国"}, {"type": "ns", "argument": "国落"}]}
{"text": "中华文化的复兴即是有中国特色的社会主义新文化的兴起。", "entity_list": [{"type": "ns", "argument": "。"}, {"type": "ns", "argument": ""}, {"type": "ns", "argument": ""}, {"type": "ns", "argument": ""}, {"type": "ns", "argument": ""}, {"type": "ns", "argument": ""}, {"type": "ns", "argument": ""}, {"type": "ns", "argument": ""}, {"type": "ns", "argument": ""}, {"type": "ns", "argument": ""}, {"type": "ns", "argument": ""}, {"type": "ns", "argument": ""}, {"type": "ns", "argument": ""}, {"type": "ns", "argument": ""}, {"type": "ns", "argument": "中"}, {"type": "ns", "argument": "中华"}, {"type": "ns", "argument": "中华文"}, {"type": "ns", "argument": "中华文化"}, {"type": "ns", "argument": "中华文化的"}, {"type": "ns", "argument": "中华文化的复"}, {"type": "ns", "argument": "中华文化的复兴"}, {"type": "ns", "argument": "中华文化的复兴即"}, {"type": "ns", "argument": "中华文化的复兴即是有"}, {"type": "ns", "argument": "中华文化的复兴即是有中"}, {"type": "ns", "argument": "中华文化的复兴即是有中国"}, {"type": "ns", "argument": "中华文化的复兴即是有中国特"}, {"type": "ns", "argument": "中华文化的复兴即是有中国特色"}, {"type": "ns", "argument": "中华文化的复兴即是有中国特色的"}, {"type": "ns", "argument": "中华文化的复兴即是有中国特色的社"}, {"type": "ns", "argument": "中华文化的复兴即是有中国特色的社会"}, {"type": "ns", "argument": "中华文化的复兴即是有中国特色的社会主"}, {"type": "ns", "argument": "中华文化的复兴即是有中国特色的社会主义"}, {"type": "ns", "argument": "中华文化的复兴即是有中国特色的社会主义新"}, {"type": "ns", "argument": "中华文化的复兴即是有中国特色的社会主义新文"}, {"type": "ns", "argument": "中华文化的复兴即是有中国特色的社会主义新文化"}, {"type": "ns", "argument": "中华文化的复兴即是有中国特色的社会主义新文化的"}, {"type": "ns", "argument": "中华文化的复兴即是有中国特色的社会主义新文化的兴"}, {"type": "ns", "argument": "中华文化的复兴即是有中国特色的社会主义新文化的兴起"}, {"type": "ns", "argument": "中华文化的复兴即是有中国特色的社会主义新文化的兴起。"}, {"type": "ns", "argument": "华"}, {"type": "ns", "argument": "华文"}, {"type": "ns", "argument": "华文化"}, {"type": "ns", "argument": "华文化的复兴即是有中"}, {"type": "ns", "argument": "华文化的复兴即是有中国"}, {"type": "ns", "argument": "华文化的复兴即是有中国特色的社会"}, {"type": "ns", "argument": "华文化的复兴即是有中国特色的社会主"}, {"type": "ns", "argument": "华文化的复兴即是有中国特色的社会主义"}, {"type": "ns", "argument": "华文化的复兴即是有中国特色的社会主义新"}, {"type": "ns", "argument": "华文化的复兴即是有中国特色的社会主义新文"}, {"type": "ns", "argument": "是有中国"}, {"type": "ns", "argument": "有中国"}, {"type": "ns", "argument": "有中国特"}, {"type": "ns", "argument": "有中国特色的社会主"}, {"type": "ns", "argument": "有中国特色的社会主义"}, {"type": "ns", "argument": "中"}, {"type": "ns", "argument": "中国"}, {"type": "ns", "argument": "中国特"}, {"type": "ns", "argument": "中国特色"}, {"type": "ns", "argument": "中国特色的"}, {"type": "ns", "argument": "中国特色的社"}, {"type": "ns", "argument": "中国特色的社会"}, {"type": "ns", "argument": "中国特色的社会主"}, {"type": "ns", "argument": "中国特色的社会主义"}, {"type": "ns", "argument": "中国特色的社会主义新"}, {"type": "ns", "argument": "中国特色的社会主义新文"}, {"type": "ns", "argument": "中国特色的社会主义新文化"}, {"type": "ns", "argument": "中国特色的社会主义新文化的"}, {"type": "ns", "argument": "中国特色的社会主义新文化的兴"}, {"type": "ns", "argument": "中国特色的社会主义新文化的兴起"}, {"type": "ns", "argument": "中国特色的社会主义新文化的兴起。"}, {"type": "ns", "argument": "国"}, {"type": "ns", "argument": "国特"}, {"type": "ns", "argument": "国特色"}, {"type": "ns", "argument": "国特色的"}, {"type": "ns", "argument": "国特色的社"}, {"type": "ns", "argument": "国特色的社会"}, {"type": "ns", "argument": "国特色的社会主"}, {"type": "ns", "argument": "国特色的社会主义"}, {"type": "ns", "argument": "国特色的社会主义新"}, {"type": "ns", "argument": "国特色的社会主义新文"}, {"type": "ns", "argument": "特色的社会主义"}, {"type": "ns", "argument": "色的社会主义"}]}
{"text": "中华民族的复兴包括中华文化的复兴。", "entity_list": [{"type": "ns", "argument": "。"}, {"type": "ns", "argument": ""}, {"type": "ns", "argument": ""}, {"type": "ns", "argument": ""}, {"type": "ns", "argument": ""}, {"type": "ns", "argument": ""}, {"type": "ns", "argument": ""}, {"type": "ns", "argument": ""}, {"type": "ns", "argument": ""}, {"type": "ns", "argument": ""}, {"type": "ns", "argument": ""}, {"type": "ns", "argument": ""}, {"type": "ns", "argument": ""}, {"type": "ns", "argument": ""}, {"type": "ns", "argument": "。"}, {"type": "ns", "argument": "中"}, {"type": "ns", "argument": "中华"}, {"type": "ns", "argument": "中华民"}, {"type": "ns", "argument": "中华民族"}, {"type": "ns", "argument": "中华民族的"}, {"type": "ns", "argument": "中华民族的复"}, {"type": "ns", "argument": "中华民族的复兴"}, {"type": "ns", "argument": "中华民族的复兴包括"}, {"type": "ns", "argument": "中华民族的复兴包括中"}, {"type": "ns", "argument": "中华民族的复兴包括中华"}, {"type": "ns", "argument": "中华民族的复兴包括中华文"}, {"type": "ns", "argument": "中华民族的复兴包括中华文化"}, {"type": "ns", "argument": "中华民族的复兴包括中华文化的"}, {"type": "ns", "argument": "中华民族的复兴包括中华文化的复"}, {"type": "ns", "argument": "中华民族的复兴包括中华文化的复兴"}, {"type": "ns", "argument": "中华民族的复兴包括中华文化的复兴。"}, {"type": "ns", "argument": "华"}, {"type": "ns", "argument": "华民"}, {"type": "ns", "argument": "华民族"}, {"type": "ns", "argument": "华民族的"}, {"type": "ns", "argument": "华民族的复"}, {"type": "ns", "argument": "华民族的复兴"}, {"type": "ns", "argument": "华民族的复兴包括中"}, {"type": "ns", "argument": "华民族的复兴包括中华"}, {"type": "ns", "argument": "华民族的复兴包括中华文"}, {"type": "ns", "argument": "华民族的复兴包括中华文化"}, {"type": "ns", "argument": "华民族的复兴包括中华文化的复"}, {"type": "ns", "argument": "华民族的复兴包括中华文化的复兴"}, {"type": "ns", "argument": "民"}, {"type": "ns", "argument": "民族"}, {"type": "ns", "argument": "民族的复兴包括中"}, {"type": "ns", "argument": "民族的复兴包括中华"}, {"type": "ns", "argument": "民族的复兴包括中华文"}, {"type": "ns", "argument": "族"}, {"type": "ns", "argument": "族的复兴包括中"}, {"type": "ns", "argument": "族的复兴包括中华"}, {"type": "ns", "argument": "的复兴包括中"}, {"type": "ns", "argument": "的复兴包括中华"}, {"type": "ns", "argument": "复兴包括中华"}, {"type": "ns", "argument": "兴包括中华"}, {"type": "ns", "argument": "包括中华"}, {"type": "ns", "argument": "括中"}, {"type": "ns", "argument": "括中华"}, {"type": "ns", "argument": "括中华文"}, {"type": "ns", "argument": "中"}, {"type": "ns", "argument": "中华"}, {"type": "ns", "argument": "中华文"}, {"type": "ns", "argument": "中华文化"}, {"type": "ns", "argument": "中华文化的"}, {"type": "ns", "argument": "中华文化的复"}, {"type": "ns", "argument": "中华文化的复兴"}, {"type": "ns", "argument": "中华文化的复兴。"}, {"type": "ns", "argument": "华"}, {"type": "ns", "argument": "华文"}]}
{"text": "二十一世纪应是中华民族伟大复兴的世纪。", "entity_list": [{"type": "ns", "argument": "是中华"}, {"type": "ns", "argument": "中华"}, {"type": "ns", "argument": "华"}]}
{"text": "此外，在史学、文学和自然科学、社会科学等方面，北大的成就也是人所共知的。", "entity_list": []}
